ilia/__init__.py
ilia/backends.py
ilia/checkers.py
ilia/ctx.py
ilia/dialects/draft202021.py
ilia/evaluators.py
ilia/loaders.py
ilia/ref.py
ilia/reg.py
ilia/res.py
ilia/validators.py
ilia-0.1.0.dist-info/WHEEL
ilia-0.1.0.dist-info/METADATA
ilia-0.1.0.dist-info/RECORD
